{
    "Country": {
        "831c8ed0-7ff2-4cf4-ac84-6d9c0c375777": {
            "country_id": "831c8ed0-7ff2-4cf4-ac84-6d9c0c375777",
            "name": "Spain",
            "code": "ES",
            "created_at": "2024-06-14T17:39:37.918180",
            "updated_at": "2024-06-14T17:39:37.918182"
        },
        "e4c150c6-aea6-4732-9add-c8a5e5a0e9e6": {
            "country_id": "e4c150c6-aea6-4732-9add-c8a5e5a0e9e6",
            "name": "France",
            "code": "FR",
            "created_at": "2024-06-15T07:05:28.058849",
            "updated_at": "2024-06-15T07:05:28.058850"
        },
        "97b74c3c-44e4-4f89-a543-4246212fa811": {
            "country_id": "97b74c3c-44e4-4f89-a543-4246212fa811",
            "name": "France",
            "code": "FR",
            "created_at": "2024-06-15T09:52:05.592380",
            "updated_at": "2024-06-15T09:52:05.592381"
        },
        "e90a0788-7c85-4518-9a06-418038edceff": {
            "country_id": "e90a0788-7c85-4518-9a06-418038edceff",
            "name": "Portugal",
            "code": "PT",
            "created_at": "2024-06-15T20:27:22.884112",
            "updated_at": "2024-06-15T20:27:22.884113"
        }
    }
}